restidy/__init__.py
restidy/gene_db_mapping.tsv
restidy/gene_drugs_mapping.tsv
restidy/restidy.py
restidy-0.2.8.dist-info/METADATA
restidy-0.2.8.dist-info/WHEEL
restidy-0.2.8.dist-info/entry_points.txt
restidy-0.2.8.dist-info/top_level.txt
restidy-0.2.8.dist-info/RECORD
