Metadata-Version: 2.1
Name: restidy
Version: 0.2.8
Summary: resfinder result tidy
Home-page: https://github.com/hbucqp/restidy
Author: Jake Cui
Author-email: cqp@cau.edu.cn
License: MIT Licence
Keywords: pip,wgs,resfinder
Platform: any
Classifier: Development Status :: 3 - Alpha
Classifier: Intended Audience :: Developers
Classifier: Topic :: Software Development :: Build Tools
Classifier: License :: OSI Approved :: MIT License
Classifier: Programming Language :: Python :: 3
Classifier: Programming Language :: Python :: 3.6
Classifier: Programming Language :: Python :: 3.7
Classifier: Programming Language :: Python :: 3.9
Requires-Dist: numpy
Requires-Dist: pandas
Requires-Dist: setuptools
